[
  {
    "type": "console.navigation/separator",
    "properties": {
      "id": "hybridsovereign-tenancy-sep",
      "perspective": "hybridsovereign",
      "name": "Tenancy"
    }
  },
  {
    "type": "console.navigation/href",
    "properties": {
      "id": "hybridsovereign-tenant-overview",
      "perspective": "hybridsovereign",
      "name": "Entity Overview",
      "href": "/hybridsovereign/tenant/overview"
    }
  },
  {
    "type": "console.navigation/href",
    "properties": {
      "id": "hybridsovereign-tenant-teams",
      "perspective": "hybridsovereign",
      "name": "Teams",
      "href": "/hybridsovereign/tenant/teams"
    }
  },
  {
    "type": "console.navigation/href",
    "properties": {
      "id": "hybridsovereign-tenant-projects",
      "perspective": "hybridsovereign",
      "name": "Projects",
      "href": "/hybridsovereign/tenant/projects"
    }
  },
  {
    "type": "console.navigation/href",
    "properties": {
      "id": "hybridsovereign-tenant-platforms",
      "perspective": "hybridsovereign",
      "name": "Platform Openshift",
      "href": "/hybridsovereign/tenant/platforms"
    }
  },
  {
    "type": "console.navigation/href",
    "properties": {
      "id": "hybridsovereign-tenant-assignments",
      "perspective": "hybridsovereign",
      "name": "Assignments",
      "href": "/hybridsovereign/tenant/assignments"
    }
  },
  {
    "type": "console.page/route",
    "properties": {
      "exact": true,
      "path": "/hybridsovereign/tenant/overview",
      "component": { "$codeRef": "TenantOverviewPage" }
    }
  },
  {
    "type": "console.page/route",
    "properties": {
      "exact": true,
      "path": "/hybridsovereign/tenant/teams",
      "component": { "$codeRef": "TenantTeamsPage" }
    }
  },
  {
    "type": "console.page/route",
    "properties": {
      "exact": true,
      "path": "/hybridsovereign/tenant/projects",
      "component": { "$codeRef": "TenantProjectsPage" }
    }
  },
  {
    "type": "console.page/route",
    "properties": {
      "exact": true,
      "path": "/hybridsovereign/tenant/platforms",
      "component": { "$codeRef": "TenantPlatformsPage" }
    }
  },
  {
    "type": "console.page/route",
    "properties": {
      "exact": true,
      "path": "/hybridsovereign/tenant/assignments",
      "component": { "$codeRef": "TenantAssignmentsPage" }
    }
  }
]
